<tv generator-info-name="youtube-live-epg" generator-info-url="https://github.com/dp247/YouTubeToM3U8">
  <channel id="exptv.tt">
    <display-name lang="en">EXP TV</display-name>
  </channel>
  <programme channel="exptv.tt" start="20251113060000 +0000" stop="20251113090000 +0000">
    <title lang="en">EXPTV_</title>
    <desc lang="en">EXP TV is a live TV channel broadcasting an endless stream of obscure media and video ephemera. EXP TV’s concept is to evoke the feeling of watching old school television, where nothing’s interactive and nothing’s on demand. Turn it on and leave it on! Schedule updates every Friday and Monday.</desc>
    <icon src="https://static-cdn.jtvnw.net/jtv_user_pictures/2ef161fc-2c34-4c8d-bc59-e0512adf0382-profile_image-300x300.png"/>
  </programme>
  <programme channel="exptv.tt" start="20251113090000 +0000" stop="20251113120000 +0000">
    <title lang="en">EXPTV_</title>
    <desc lang="en">EXP TV is a live TV channel broadcasting an endless stream of obscure media and video ephemera. EXP TV’s concept is to evoke the feeling of watching old school television, where nothing’s interactive and nothing’s on demand. Turn it on and leave it on! Schedule updates every Friday and Monday.</desc>
    <icon src="https://static-cdn.jtvnw.net/jtv_user_pictures/2ef161fc-2c34-4c8d-bc59-e0512adf0382-profile_image-300x300.png"/>
  </programme>
  <programme channel="exptv.tt" start="20251113120000 +0000" stop="20251113150000 +0000">
    <title lang="en">EXPTV_</title>
    <desc lang="en">EXP TV is a live TV channel broadcasting an endless stream of obscure media and video ephemera. EXP TV’s concept is to evoke the feeling of watching old school television, where nothing’s interactive and nothing’s on demand. Turn it on and leave it on! Schedule updates every Friday and Monday.</desc>
    <icon src="https://static-cdn.jtvnw.net/jtv_user_pictures/2ef161fc-2c34-4c8d-bc59-e0512adf0382-profile_image-300x300.png"/>
  </programme>
  <programme channel="exptv.tt" start="20251113150000 +0000" stop="20251113180000 +0000">
    <title lang="en">EXPTV_</title>
    <desc lang="en">EXP TV is a live TV channel broadcasting an endless stream of obscure media and video ephemera. EXP TV’s concept is to evoke the feeling of watching old school television, where nothing’s interactive and nothing’s on demand. Turn it on and leave it on! Schedule updates every Friday and Monday.</desc>
    <icon src="https://static-cdn.jtvnw.net/jtv_user_pictures/2ef161fc-2c34-4c8d-bc59-e0512adf0382-profile_image-300x300.png"/>
  </programme>
  <programme channel="exptv.tt" start="20251113180000 +0000" stop="20251113210000 +0000">
    <title lang="en">EXPTV_</title>
    <desc lang="en">EXP TV is a live TV channel broadcasting an endless stream of obscure media and video ephemera. EXP TV’s concept is to evoke the feeling of watching old school television, where nothing’s interactive and nothing’s on demand. Turn it on and leave it on! Schedule updates every Friday and Monday.</desc>
    <icon src="https://static-cdn.jtvnw.net/jtv_user_pictures/2ef161fc-2c34-4c8d-bc59-e0512adf0382-profile_image-300x300.png"/>
  </programme>
  <programme channel="exptv.tt" start="20251113210000 +0000" stop="20251114000000 +0000">
    <title lang="en">EXPTV_</title>
    <desc lang="en">EXP TV is a live TV channel broadcasting an endless stream of obscure media and video ephemera. EXP TV’s concept is to evoke the feeling of watching old school television, where nothing’s interactive and nothing’s on demand. Turn it on and leave it on! Schedule updates every Friday and Monday.</desc>
    <icon src="https://static-cdn.jtvnw.net/jtv_user_pictures/2ef161fc-2c34-4c8d-bc59-e0512adf0382-profile_image-300x300.png"/>
  </programme>
  <programme channel="exptv.tt" start="20251114000000 +0000" stop="20251114030000 +0000">
    <title lang="en">EXPTV_</title>
    <desc lang="en">EXP TV is a live TV channel broadcasting an endless stream of obscure media and video ephemera. EXP TV’s concept is to evoke the feeling of watching old school television, where nothing’s interactive and nothing’s on demand. Turn it on and leave it on! Schedule updates every Friday and Monday.</desc>
    <icon src="https://static-cdn.jtvnw.net/jtv_user_pictures/2ef161fc-2c34-4c8d-bc59-e0512adf0382-profile_image-300x300.png"/>
  </programme>
  <programme channel="exptv.tt" start="20251114030000 +0000" stop="20251114060000 +0000">
    <title lang="en">EXPTV_</title>
    <desc lang="en">EXP TV is a live TV channel broadcasting an endless stream of obscure media and video ephemera. EXP TV’s concept is to evoke the feeling of watching old school television, where nothing’s interactive and nothing’s on demand. Turn it on and leave it on! Schedule updates every Friday and Monday.</desc>
    <icon src="https://static-cdn.jtvnw.net/jtv_user_pictures/2ef161fc-2c34-4c8d-bc59-e0512adf0382-profile_image-300x300.png"/>
  </programme>
</tv>
